{
    "version": "144.0.7559.133",
    "description": "Fast, secure, and free web browser, built for the modern web.",
    "homepage": "https://www.google.com/chrome/",
    "license": {
        "identifier": "Freeware",
        "url": "https://www.google.com/chrome/privacy/eula_text.html"
    },
    "architecture": {
        "64bit": {
            "url": "https://dl.google.com/release2/chrome/ace6zn6fr5cgu25rmizns7oamjoa_144.0.7559.133/144.0.7559.133_chrome_installer_uncompressed.exe#/dl.7z",
            "hash": "99ecca4fb028a32a11c344b0a16ef7dd5bc6b38f3bdbc4acf998c06946422f56"
        },
        "32bit": {
            "url": "https://dl.google.com/release2/chrome/acw2xz4tfj7k5bp6r7l53svhuktq_144.0.7559.133/144.0.7559.133_chrome_installer_uncompressed.exe#/dl.7z",
            "hash": "cb4b6c8aaddeaa695021e6a35d1cf2410f81a7e2bc60f23d8dad1c39e6506799"
        },
        "arm64": {
            "url": "https://dl.google.com/release2/chrome/adjlojv5qioc65jotqkbs6bboxka_144.0.7559.133/144.0.7559.133_chrome_installer_uncompressed.exe#/dl.7z",
            "hash": "89b8edb2b3e77b76603f1ffc9bfc503c52870dafd848ac8f7a2ca00800ef8e6d"
        }
    },
    "extract_dir": "Chrome-bin",
    "bin": "chrome.exe",
    "shortcuts": [
        [
            "chrome.exe",
            "Google Chrome"
        ]
    ],
    "env_set": {
        "CHROME_EXECUTABLE": "$dir\\chrome.exe"
    },
    "installer": {
        "script": [
            ". \"$bucketsdir\\$bucket\\bin\\utils.ps1\"",
            "New-PersistDirectory \"$env:LocalAppData\\Google\\Chrome\\User Data\" \"$persist_dir\\User Data\" -Migrate"
        ]
    },
    "pre_uninstall": [
        "$bucket = $install.bucket",
        ". \"$bucketsdir\\$bucket\\bin\\utils.ps1\"",
        "Stop-App",
        "Remove-Junction \"$env:LocalAppData\\Google\\Chrome\\User Data\""
    ],
    "uninstaller": {
        "script": [
            "if ($cmd -eq 'uninstall') {",
            "    Remove-Item -Path \"$env:LOCALAPPDATA\\Google\\Chrome\" -Recurse -Force -ErrorAction SilentlyContinue | Out-Null",
            "    Remove-Item -Path HKCU:\\SOFTWARE\\Google\\Chrome -Recurse -Force -ErrorAction SilentlyContinue | Out-Null",
            "}"
        ]
    },
    "checkver": {
        "script": [
            "$data = Invoke-RestMethod -Uri \"https://raw.githubusercontent.com/Bush2021/chrome_installer/refs/heads/main/data.json\"",
            "\"=====version=====\" + $data.win_stable_x64.version +",
            "\"=====x64=====\" + ($data.win_stable_x64.urls | Where-Object { $_ -match \"^https://dl.google.com\" } | Select-Object -First 1) +",
            "\"=====x86=====\" + ($data.win_stable_x86.urls | Where-Object { $_ -match \"^https://dl.google.com\" } | Select-Object -First 1) +",
            "\"=====arm64=====\" + ($data.win_stable_arm64.urls | Where-Object { $_ -match \"^https://dl.google.com\" } | Select-Object -First 1)"
        ],
        "regex": "=====version=====(.+)=====x64=====(?<x64>.+)=====x86=====(?<x86>.+)=====arm64=====(?<arm64>.+)"
    },
    "autoupdate": {
        "architecture": {
            "64bit": {
                "url": "$matchX64#/dl.7z",
                "hash": {
                    "url": "https://raw.githubusercontent.com/Bush2021/chrome_installer/refs/heads/main/data.json",
                    "jsonpath": "$.win_stable_x64.sha256"
                }
            },
            "32bit": {
                "url": "$matchX86#/dl.7z",
                "hash": {
                    "url": "https://raw.githubusercontent.com/Bush2021/chrome_installer/refs/heads/main/data.json",
                    "jsonpath": "$.win_stable_x86.sha256"
                }
            },
            "arm64": {
                "url": "$matchArm64#/dl.7z",
                "hash": {
                    "url": "https://raw.githubusercontent.com/Bush2021/chrome_installer/refs/heads/main/data.json",
                    "jsonpath": "$.win_stable_arm64.sha256"
                }
            }
        }
    }
}
