{
    "version": "2.36.1",
    "description": "一个输入法状态提示工具。An input method status tip tool.",
    "homepage": "https://github.com/abgox/InputTip",
    "license": {
        "identifier": "MIT",
        "url": "https://github.com/abgox/InputTip/blob/main/LICENSE"
    },
    "url": "https://github.com/abgox/InputTip/releases/download/v2.36.1/InputTip.zip",
    "hash": "9f1dcf2c66a58f99f690c3a43f6b3fc131a2c803974826f9e8c936fea20bcfd3",
    "extract_dir": "InputTip",
    "shortcuts": [
        [
            "InputTip.exe",
            "InputTip"
        ]
    ],
    "pre_install": [
        "if (!(Test-Path \"$persist_dir\")) { $null = New-Item -ItemType Directory \"$persist_dir\" };",
        "if (!(Test-Path \"$persist_dir\\InputTip.ini\")) { '' | Out-File \"$persist_dir\\InputTip.ini\" -Encoding UTF8 -Force }"
    ],
    "persist": "InputTip.ini",
    "checkver": "github",
    "autoupdate": {
        "url": "https://github.com/abgox/InputTip/releases/download/v$version/InputTip.zip"
    }
}
